apipkg/__init__.py
apipkg/_alias_module.py
apipkg/_importing.py
apipkg/_module.py
apipkg/_syncronized.py
apipkg/_version.py
apipkg/py.typed
apipkg-3.0.1.dist-info/METADATA
apipkg-3.0.1.dist-info/WHEEL
apipkg-3.0.1.dist-info/entry_points.txt
apipkg-3.0.1.dist-info/license_files/LICENSE
apipkg-3.0.1.dist-info/RECORD
